[{"kind":"PluginModule","metadata":{"name":"StaticListVariable","version":"0.8.0-rc.0"},"spec":{"schemasPath":"schemas","plugins":[{"kind":"Variable","spec":{"display":{"name":"Static List Variable"},"name":"StaticListVariable"}}]},"status":{"isLoaded":true,"inDev":false}},{"kind":"PluginModule","metadata":{"name":"HeatMapChart","version":"0.4.0-rc.0"},"spec":{"schemasPath":"schemas","plugins":[{"kind":"Panel","spec":{"display":{"name":"HeatMap Chart"},"name":"HeatMapChart"}}]},"status":{"isLoaded":true,"inDev":false}},{"kind":"PluginModule","metadata":{"name":"FlameChart","version":"0.5.0-rc.0"},"spec":{"schemasPath":"schemas","plugins":[{"kind":"Panel","spec":{"display":{"name":"Flame Chart"},"name":"FlameChart"}}]},"status":{"isLoaded":true,"inDev":false}},{"kind":"PluginModule","metadata":{"name":"ClickHouse","version":"0.5.0-rc.0"},"spec":{"schemasPath":"schemas","moduleName":"ClickHouse","plugins":[{"kind":"Datasource","spec":{"display":{"name":"ClickHouse Datasource"},"name":"ClickHouseDatasource"}},{"kind":"TimeSeriesQuery","spec":{"display":{"name":"ClickHouse Time Series Query"},"name":"ClickHouseTimeSeriesQuery"}},{"kind":"LogQuery","spec":{"display":{"name":"ClickHouse Log Query"},"name":"ClickHouseLogQuery"}}]},"status":{"isLoaded":true,"inDev":false}},{"kind":"PluginModule","metadata":{"name":"Table","version":"0.11.0-rc.0"},"spec":{"schemasPath":"schemas","plugins":[{"kind":"Panel","spec":{"display":{"name":"Table"},"name":"Table"}}]},"status":{"isLoaded":true,"inDev":false}},{"kind":"PluginModule","metadata":{"name":"PieChart","version":"0.13.0-rc.0"},"spec":{"schemasPath":"schemas","plugins":[{"kind":"Panel","spec":{"display":{"name":"Pie Chart"},"name":"PieChart"}}]},"status":{"isLoaded":true,"inDev":false}},{"kind":"PluginModule","metadata":{"name":"TimeSeriesChart","version":"0.12.0-rc.0"},"spec":{"schemasPath":"schemas","plugins":[{"kind":"Panel","spec":{"display":{"name":"Time Series Chart"},"name":"TimeSeriesChart"}}]},"status":{"isLoaded":true,"inDev":false}},{"kind":"PluginModule","metadata":{"name":"TimeSeriesTable","version":"0.11.0-rc.0"},"spec":{"schemasPath":"schemas","plugins":[{"kind":"Panel","spec":{"display":{"name":"Time Series Table"},"name":"TimeSeriesTable"}}]},"status":{"isLoaded":true,"inDev":false}},{"kind":"PluginModule","metadata":{"name":"HistogramChart","version":"0.11.0-rc.0"},"spec":{"schemasPath":"schemas","plugins":[{"kind":"Panel","spec":{"display":{"name":"Histogram Chart"},"name":"HistogramChart"}}]},"status":{"isLoaded":true,"inDev":false}},{"kind":"PluginModule","metadata":{"name":"Markdown","version":"0.11.0-rc.0"},"spec":{"schemasPath":"schemas","plugins":[{"kind":"Panel","spec":{"display":{"name":"Markdown"},"name":"Markdown"}}]},"status":{"isLoaded":true,"inDev":false}},{"kind":"PluginModule","metadata":{"name":"Pyroscope","version":"0.5.0-rc.0"},"spec":{"schemasPath":"schemas","plugins":[{"kind":"Datasource","spec":{"display":{"name":"Pyroscope Datasource"},"name":"PyroscopeDatasource"}},{"kind":"ProfileQuery","spec":{"display":{"name":"Pyroscope Profile Query"},"name":"PyroscopeProfileQuery"}},{"kind":"Explore","spec":{"display":{"name":"Pyroscope Explorer"},"name":"PyroscopeExplorer"}}]},"status":{"isLoaded":true,"inDev":false}},{"kind":"PluginModule","metadata":{"name":"StatChart","version":"0.12.0-rc.0"},"spec":{"schemasPath":"schemas","plugins":[{"kind":"Panel","spec":{"display":{"name":"Stat Chart"},"name":"StatChart"}}]},"status":{"isLoaded":true,"inDev":false}},{"kind":"PluginModule","metadata":{"name":"GaugeChart","version":"0.12.0-rc.0"},"spec":{"schemasPath":"schemas","plugins":[{"kind":"Panel","spec":{"display":{"name":"Gauge Chart"},"name":"GaugeChart"}}]},"status":{"isLoaded":true,"inDev":false}},{"kind":"PluginModule","metadata":{"name":"ScatterChart","version":"0.10.0-rc.0"},"spec":{"schemasPath":"schemas","plugins":[{"kind":"Panel","spec":{"display":{"name":"Scatter Chart"},"name":"ScatterChart"}}]},"status":{"isLoaded":true,"inDev":false}},{"kind":"PluginModule","metadata":{"name":"Tempo","version":"0.57.0-rc.0"},"spec":{"schemasPath":"schemas","plugins":[{"kind":"Datasource","spec":{"display":{"name":"Tempo Datasource"},"name":"TempoDatasource"}},{"kind":"TraceQuery","spec":{"display":{"name":"Tempo Trace Query"},"name":"TempoTraceQuery"}},{"kind":"Explore","spec":{"display":{"name":"Tempo Traces Explorer"},"name":"TempoExplorer"}}]},"status":{"isLoaded":true,"inDev":false}},{"kind":"PluginModule","metadata":{"name":"TracingGanttChart","version":"0.12.0-rc.0"},"spec":{"schemasPath":"schemas","plugins":[{"kind":"Panel","spec":{"display":{"name":"Tracing Gantt Chart"},"name":"TracingGanttChart"}}]},"status":{"isLoaded":true,"inDev":false}},{"kind":"PluginModule","metadata":{"name":"LogsTable","version":"0.2.0-rc.0"},"spec":{"schemasPath":"schemas","plugins":[{"kind":"Panel","spec":{"display":{"name":"Logs Table"},"name":"LogsTable"}}]},"status":{"isLoaded":true,"inDev":false}},{"kind":"PluginModule","metadata":{"name":"Prometheus","version":"0.57.0-rc.0"},"spec":{"schemasPath":"schemas","plugins":[{"kind":"Datasource","spec":{"display":{"name":"Prometheus Datasource"},"name":"PrometheusDatasource"}},{"kind":"TimeSeriesQuery","spec":{"display":{"name":"Prometheus Time Series Query"},"name":"PrometheusTimeSeriesQuery"}},{"kind":"Variable","spec":{"display":{"name":"Prometheus Label Values Variable"},"name":"PrometheusLabelValuesVariable"}},{"kind":"Variable","spec":{"display":{"name":"Prometheus Label Names Variable"},"name":"PrometheusLabelNamesVariable"}},{"kind":"Variable","spec":{"display":{"name":"Prometheus PromQL Variable"},"name":"PrometheusPromQLVariable"}},{"kind":"Explore","spec":{"display":{"name":"Prometheus Explorer"},"name":"PrometheusExplorer"}}]},"status":{"isLoaded":true,"inDev":false}},{"kind":"PluginModule","metadata":{"name":"TraceTable","version":"0.10.0-rc.0"},"spec":{"schemasPath":"schemas","plugins":[{"kind":"Panel","spec":{"display":{"name":"Trace Table"},"name":"TraceTable"}}]},"status":{"isLoaded":true,"inDev":false}},{"kind":"PluginModule","metadata":{"name":"VictoriaLogs","version":"0.3.0-rc.0"},"spec":{"schemasPath":"schemas","moduleName":"VictoriaLogs","plugins":[{"kind":"Datasource","spec":{"display":{"name":"VictoriaLogs Datasource"},"name":"VictoriaLogsDatasource"}},{"kind":"TimeSeriesQuery","spec":{"display":{"name":"VictoriaLogs Time Series Query"},"name":"VictoriaLogsTimeSeriesQuery"}},{"kind":"LogQuery","spec":{"display":{"name":"VictoriaLogs Log Query"},"name":"VictoriaLogsLogQuery"}},{"kind":"Variable","spec":{"display":{"name":"VictoriaLogs Field Values Variable"},"name":"VictoriaLogsFieldValuesVariable"}},{"kind":"Variable","spec":{"display":{"name":"VictoriaLogs Field Names Variable"},"name":"VictoriaLogsFieldNamesVariable"}}]},"status":{"isLoaded":true,"inDev":false}},{"kind":"PluginModule","metadata":{"name":"DatasourceVariable","version":"0.5.0-rc.0"},"spec":{"schemasPath":"schemas","plugins":[{"kind":"Variable","spec":{"display":{"name":"Datasource Variable"},"name":"DatasourceVariable"}}]},"status":{"isLoaded":true,"inDev":false}},{"kind":"PluginModule","metadata":{"name":"StatusHistoryChart","version":"0.12.0-rc.0"},"spec":{"schemasPath":"schemas","plugins":[{"kind":"Panel","spec":{"display":{"name":"Status History Chart"},"name":"StatusHistoryChart"}}]},"status":{"isLoaded":true,"inDev":false}},{"kind":"PluginModule","metadata":{"name":"BarChart","version":"0.11.0-rc.0"},"spec":{"schemasPath":"schemas","plugins":[{"kind":"Panel","spec":{"display":{"name":"Bar Chart"},"name":"BarChart"}}]},"status":{"isLoaded":true,"inDev":false}},{"kind":"PluginModule","metadata":{"name":"Loki","version":"0.5.0-rc.0"},"spec":{"schemasPath":"schemas","moduleName":"Loki","plugins":[{"kind":"Datasource","spec":{"display":{"name":"Loki Datasource"},"name":"LokiDatasource"}},{"kind":"TimeSeriesQuery","spec":{"display":{"name":"Loki Time Series Query"},"name":"LokiTimeSeriesQuery"}},{"kind":"LogQuery","spec":{"display":{"name":"Loki Log Query"},"name":"LokiLogQuery"}}]},"status":{"isLoaded":true,"inDev":false}}]